simplegan/__init__.py
simplegan/autoencoder/__init__.py
simplegan/autoencoder/convolutional_autoencoder.py
simplegan/autoencoder/vae.py
simplegan/autoencoder/vanilla_autoencoder.py
simplegan/autoencoder/vq_vae.py
simplegan/datasets/__init__.py
simplegan/datasets/load_cifar10.py
simplegan/datasets/load_cifar100.py
simplegan/datasets/load_custom_data.py
simplegan/datasets/load_cyclegan_datasets.py
simplegan/datasets/load_lsun.py
simplegan/datasets/load_mnist.py
simplegan/datasets/load_pix2pix_datasets.py
simplegan/gan/__init__.py
simplegan/gan/cgan.py
simplegan/gan/cyclegan.py
simplegan/gan/dcgan.py
simplegan/gan/infogan.py
simplegan/gan/pix2pix.py
simplegan/gan/vanilla_gan.py
simplegan/gan/wgan.py
simplegan/losses/__init__.py
simplegan/losses/cyclegan_loss.py
simplegan/losses/infogan_loss.py
simplegan/losses/minmax_loss.py
simplegan/losses/mse_loss.py
simplegan/losses/pix2pix_loss.py
simplegan/losses/vae_loss.py
simplegan/losses/wasserstein_loss.py
simplegan-0.2.8.dist-info/LICENSE
simplegan-0.2.8.dist-info/METADATA
simplegan-0.2.8.dist-info/WHEEL
simplegan-0.2.8.dist-info/top_level.txt
simplegan-0.2.8.dist-info/RECORD
