Metadata-Version: 2.1
Name: simplegan
Version: 0.2.8
Summary: Framework to ease training of generative models based on TensorFlow
Home-page: https://github.com/grohith327
Author: Rohith Gandhi G
Author-email: grohith327@gmail.com
License: MIT
Keywords: GAN,Computer Vision,Deep Learning,TensorFlow,Generative Models,Neural Networks,AI
Platform: UNKNOWN
Classifier: Development Status :: 5 - Production/Stable
Classifier: Intended Audience :: Developers
Classifier: Topic :: Software Development :: Build Tools
Classifier: Topic :: Scientific/Engineering :: Artificial Intelligence
Classifier: Topic :: Scientific/Engineering :: Image Recognition
Classifier: Operating System :: OS Independent
Classifier: License :: OSI Approved :: MIT License
Classifier: Programming Language :: Python :: 3
Classifier: Programming Language :: Python :: 3.4
Classifier: Programming Language :: Python :: 3.5
Classifier: Programming Language :: Python :: 3.6
Classifier: Programming Language :: Python :: 3.7
Requires-Dist: tensorflow (==2.0.1)
Requires-Dist: tqdm
Requires-Dist: numpy
Requires-Dist: opencv-python
Requires-Dist: imageio
Requires-Dist: tensorflow-datasets
